open_quant_data/__init__.py
open_quant_data/dataset/CsvUtils.py
open_quant_data/dataset/Dataset.py
open_quant_data/dataset/DatasetConfig.py
open_quant_data/dataset/__init__.py
open_quant_data/dataset/thirdparty/__init__.py
open_quant_data/dataset/thirdparty/akshare/AkshareDataset.py
open_quant_data/dataset/thirdparty/akshare/__init__.py
open_quant_data/dataset/thirdparty/xtquant/XtquantDataset.py
open_quant_data/dataset/thirdparty/xtquant/__init__.py
open_quant_data/model/Period.py
open_quant_data/model/StockData.py
open_quant_data/model/StockDataTimed.py
open_quant_data/model/TimeSegment.py
open_quant_data/model/__init__.py
open_quant_data/mysql/MysqlUtils.py
open_quant_data/mysql/__init__.py
open_quant_data/stat/BondUtils.py
open_quant_data/stat/KDJUtils.py
open_quant_data/stat/LabelUtils.py
open_quant_data/stat/MACDUtils.py
open_quant_data/stat/MomentumUtils.py
open_quant_data/stat/RSIUtils.py
open_quant_data/stat/__init__.py
open_quant_data/utils/Configuration.py
open_quant_data/utils/__init__.py
open_quant_data-0.3.2.dist-info/LICENSE
open_quant_data-0.3.2.dist-info/METADATA
open_quant_data-0.3.2.dist-info/WHEEL
open_quant_data-0.3.2.dist-info/top_level.txt
open_quant_data-0.3.2.dist-info/RECORD
