Metadata-Version: 2.1
Name: open-quant-data
Version: 0.3.2
Summary: open quant data
Home-page: https://github.com/openhe-hub/open-quant-data.git
Author: openhe
Author-email: hezhewen2004@gmail.com
Classifier: Programming Language :: Python :: 3
Classifier: License :: OSI Approved :: MIT License
Classifier: Operating System :: OS Independent
License-File: LICENSE
